checkadmin/__init__.py
checkadmin/apps.py
checkadmin/checks.py
django_check_admin-1.2.0.dist-info/LICENSE
django_check_admin-1.2.0.dist-info/METADATA
django_check_admin-1.2.0.dist-info/WHEEL
django_check_admin-1.2.0.dist-info/top_level.txt
django_check_admin-1.2.0.dist-info/RECORD
